.gitignore
.travis.yml
LICENSE
LICENSE.TL
MANIFEST.in
README.md
setup.cfg
setup.py
texlive2015.tlpdb.gz
texlive2016.tlpdb.gz
texlive2017.tlpdb.gz
texscyther
test/basic.tlpdb
test/conftest.py
test/error_files_not_indented.tlpdb
test/error_missing_archpkg.tlpdb
test/error_nonexistent_dep.tlpdb
test/error_unknown_filetype.tlpdb
test/error_weird_line_postfix.tlpdb
test/helper.py
test/test_arch.py
test/test_basic.py
test/test_dirs.py
test/test_errors.py
test/test_orm.py
test/test_regex.py
test/test_texlive.py
texscythe/__init__.py
texscythe/config.py
texscythe/orm.py
texscythe/subset.py
texscythe/tlpdbparser.py
texscythe.egg-info/PKG-INFO
texscythe.egg-info/SOURCES.txt
texscythe.egg-info/dependency_links.txt
texscythe.egg-info/requires.txt
texscythe.egg-info/top_level.txt