Metadata-Version: 1.1
Name: texscythe
Version: 0.3.1
Summary: TeX Live texmf subsetter
Home-page: https://github.com/vext01/texscythe
Author: Edd Barrett
Author-email: edd@theunixzoo.co.uk
License: ISC
Keywords: LaTeX texmf subset
Platform: UNKNOWN
Classifier: Development Status :: 4 - Beta
Classifier: Environment :: Console
Classifier: License :: OSI Approved
Classifier: Operating System :: OS Independent
Classifier: Programming Language :: Python :: 2.7
Classifier: Topic :: Text Processing :: Markup :: LaTeX
